home/tnkteja/.mypy/myhelp/tags.xml
myhelp/__init__.py
myhelp/myhelp.py
myhelp-1.0.0.dist-info/DESCRIPTION.rst
myhelp-1.0.0.dist-info/RECORD
myhelp-1.0.0.dist-info/WHEEL
myhelp-1.0.0.dist-info/metadata.json
myhelp-1.0.0.dist-info/entry_points.txt
myhelp-1.0.0.dist-info/METADATA
myhelp-1.0.0.dist-info/top_level.txt
