Metadata-Version: 2.0
Name: myhelp
Version: 1.0.0
Summary: myhelp
Home-page: https://github.com/tnkteja/myhelp.git
Author: Neela Krishna Teja Tadikonda
Author-email: tnkteja@gmail.com
License: MIT
Keywords: sample setuptools development
Platform: UNKNOWN
Classifier: Development Status :: 3 - Alpha
Classifier: Intended Audience :: Developers
Classifier: Topic :: Software Development :: Build Tools
Classifier: License :: OSI Approved :: MIT License
Classifier: Programming Language :: Python :: 2.6
Classifier: Programming Language :: Python :: 2.7
Classifier: Programming Language :: Python :: 3
Classifier: Programming Language :: Python :: 3.2
Classifier: Programming Language :: Python :: 3.3
Classifier: Programming Language :: Python :: 3.4
